colliderscope/__init__.py
colliderscope/_version.py
colliderscope/plot.py
colliderscope-0.0.1.dist-info/LICENSE.txt
colliderscope-0.0.1.dist-info/METADATA
colliderscope-0.0.1.dist-info/WHEEL
colliderscope-0.0.1.dist-info/top_level.txt
colliderscope-0.0.1.dist-info/RECORD
