Metadata-Version: 2.1
Name: colliderscope
Version: 0.0.1
Summary: Plotting tools for Monte-Carlo particle showers.
Home-page: https://github.com/jacanchaplais/colliderscope
Author: Jacan Chaplais
Author-email: jacanchaplais@gmail.com
License: BSD 3-Clause License
Platform: UNKNOWN
Classifier: Programming Language :: Python :: 3
Classifier: License :: OSI Approved :: BSD License
Classifier: Operating System :: OS Independent
License-File: LICENSE.txt
Requires-Dist: numpy
Requires-Dist: pandas
Requires-Dist: networkx
Requires-Dist: scipy
Requires-Dist: pyvis
Requires-Dist: colour
Requires-Dist: mcpid
